effgen/__init__.py
effgen/cli.py
effgen/py.typed
effgen/config/__init__.py
effgen/config/loader.py
effgen/config/validator.py
effgen/config/schemas/agent_config.schema.json
effgen/config/schemas/model_config.schema.json
effgen/config/schemas/tool_config.schema.json
effgen/core/__init__.py
effgen/core/agent.py
effgen/core/complexity_analyzer.py
effgen/core/decomposition_engine.py
effgen/core/execution_tracker.py
effgen/core/orchestrator.py
effgen/core/router.py
effgen/core/state.py
effgen/core/sub_agent_manager.py
effgen/core/task.py
effgen/execution/__init__.py
effgen/execution/docker_sandbox.py
effgen/execution/sandbox.py
effgen/execution/validators.py
effgen/gpu/__init__.py
effgen/gpu/allocator.py
effgen/gpu/monitor.py
effgen/gpu/utils.py
effgen/memory/__init__.py
effgen/memory/long_term.py
effgen/memory/short_term.py
effgen/memory/vector_store.py
effgen/models/__init__.py
effgen/models/anthropic_adapter.py
effgen/models/base.py
effgen/models/gemini_adapter.py
effgen/models/model_loader.py
effgen/models/openai_adapter.py
effgen/models/transformers_engine.py
effgen/models/vllm_engine.py
effgen/prompts/__init__.py
effgen/prompts/chain_manager.py
effgen/prompts/optimizer.py
effgen/prompts/template_manager.py
effgen/prompts/templates/analysis.yaml
effgen/prompts/templates/coding.yaml
effgen/prompts/templates/general.yaml
effgen/prompts/templates/reasoning.yaml
effgen/tools/__init__.py
effgen/tools/base_tool.py
effgen/tools/registry.py
effgen/tools/builtin/__init__.py
effgen/tools/builtin/calculator.py
effgen/tools/builtin/code_executor.py
effgen/tools/builtin/file_ops.py
effgen/tools/builtin/python_repl.py
effgen/tools/builtin/web_search.py
effgen/tools/protocols/__init__.py
effgen/tools/protocols/a2a/__init__.py
effgen/tools/protocols/a2a/agent_card.py
effgen/tools/protocols/a2a/client.py
effgen/tools/protocols/a2a/protocol.py
effgen/tools/protocols/acp/__init__.py
effgen/tools/protocols/acp/client.py
effgen/tools/protocols/acp/protocol.py
effgen-0.0.1.dist-info/licenses/LICENSE
effgen-0.0.1.dist-info/METADATA
effgen-0.0.1.dist-info/WHEEL
effgen-0.0.1.dist-info/entry_points.txt
effgen-0.0.1.dist-info/top_level.txt
effgen-0.0.1.dist-info/RECORD
