Metadata-Version: 2.4
Name: effgen
Version: 0.0.1
Summary: A comprehensive framework for building agents with Small Language Models
Home-page: https://github.com/ctrl-gaurav/effGen
Author: Gaurav Srivastava
Author-email: Gaurav Srivastava <gks@vt.edu>
Maintainer-email: Gaurav Srivastava <gks@vt.edu>
License: MIT
Project-URL: Homepage, https://effgen.org/
Project-URL: Documentation, https://effgen.org/docs/
Project-URL: Repository, https://github.com/ctrl-gaurav/effGen
Project-URL: Bug Tracker, https://github.com/ctrl-gaurav/effGen/issues
Project-URL: Changelog, https://github.com/ctrl-gaurav/effGen/blob/main/CHANGELOG.md
Keywords: ai,agents,llm,slm,language-models,small-language-models,tool-use,function-calling,prompt-engineering,multi-agent,agent-framework,transformers,vllm,openai,anthropic,gemini
Classifier: Development Status :: 3 - Alpha
Classifier: Intended Audience :: Developers
Classifier: Intended Audience :: Science/Research
Classifier: Intended Audience :: Education
Classifier: License :: OSI Approved :: MIT License
Classifier: Operating System :: OS Independent
Classifier: Programming Language :: Python :: 3
Classifier: Programming Language :: Python :: 3.8
Classifier: Programming Language :: Python :: 3.9
Classifier: Programming Language :: Python :: 3.10
Classifier: Programming Language :: Python :: 3.11
Classifier: Programming Language :: Python :: 3.12
Classifier: Topic :: Scientific/Engineering :: Artificial Intelligence
Classifier: Topic :: Software Development :: Libraries :: Python Modules
Classifier: Framework :: AsyncIO
Classifier: Typing :: Typed
Requires-Python: >=3.8
License-File: LICENSE
Requires-Dist: torch>=2.0.0
Requires-Dist: transformers>=4.35.0
Requires-Dist: accelerate>=0.24.0
Requires-Dist: safetensors>=0.4.0
Requires-Dist: sentencepiece>=0.1.99
Requires-Dist: protobuf>=3.20.0
Requires-Dist: openai>=1.3.0
Requires-Dist: anthropic>=0.7.0
Requires-Dist: google-generativeai>=0.3.0
Requires-Dist: pyyaml>=6.0.1
Requires-Dist: jsonschema>=4.19.0
Requires-Dist: json5>=0.9.14
Requires-Dist: python-dotenv>=1.0.0
Requires-Dist: requests>=2.31.0
Requires-Dist: aiohttp>=3.9.0
Requires-Dist: httpx>=0.25.0
Requires-Dist: duckduckgo-search>=8.1.0
Requires-Dist: ddgs>=9.9.3
Requires-Dist: docker>=6.1.0
Requires-Dist: nbformat>=5.9.0
Requires-Dist: jupyter-client>=8.5.0
Requires-Dist: numpy>=1.24.0
Requires-Dist: pandas>=2.0.0
Requires-Dist: pydantic>=2.0.0
Requires-Dist: tqdm>=4.66.0
Requires-Dist: rich>=13.7.0
Requires-Dist: click>=8.1.0
Requires-Dist: colorama>=0.4.6
Requires-Dist: jinja2>=3.1.0
Requires-Dist: asyncio-throttle>=1.0.1
Requires-Dist: nest-asyncio>=1.5.8
Requires-Dist: loguru>=0.7.0
Requires-Dist: gputil>=1.4.0
Requires-Dist: nvidia-ml-py>=11.495.46
Requires-Dist: mcp>=1.25.0
Requires-Dist: psutil>=5.9.0
Requires-Dist: tiktoken>=0.5.0
Requires-Dist: scikit-learn>=1.3.0
Requires-Dist: cryptography>=41.0.0
Provides-Extra: dev
Requires-Dist: pytest>=7.4.0; extra == "dev"
Requires-Dist: pytest-asyncio>=0.21.0; extra == "dev"
Requires-Dist: pytest-cov>=4.1.0; extra == "dev"
Requires-Dist: black>=23.12.0; extra == "dev"
Requires-Dist: isort>=5.13.0; extra == "dev"
Requires-Dist: flake8>=6.1.0; extra == "dev"
Requires-Dist: mypy>=1.7.0; extra == "dev"
Provides-Extra: vllm
Requires-Dist: vllm>=0.2.7; extra == "vllm"
Provides-Extra: flash-attn
Requires-Dist: flash-attn>=2.3.0; extra == "flash-attn"
Provides-Extra: vector-db
Requires-Dist: faiss-cpu>=1.7.4; extra == "vector-db"
Requires-Dist: chromadb>=0.4.18; extra == "vector-db"
Requires-Dist: qdrant-client>=1.7.0; extra == "vector-db"
Provides-Extra: search
Requires-Dist: duckduckgo-search>=8.1.0; extra == "search"
Requires-Dist: google-search-results>=2.4.2; extra == "search"
Requires-Dist: google-api-python-client>=2.108.0; extra == "search"
Provides-Extra: all
Requires-Dist: vllm>=0.2.7; extra == "all"
Requires-Dist: flash-attn>=2.3.0; extra == "all"
Requires-Dist: faiss-cpu>=1.7.4; extra == "all"
Requires-Dist: chromadb>=0.4.18; extra == "all"
Requires-Dist: qdrant-client>=1.7.0; extra == "all"
Dynamic: author
Dynamic: home-page
Dynamic: license-file
Dynamic: requires-python
